oanda_accessor_pyv20/__init__.py
oanda_accessor_pyv20/api.py
oanda_accessor_pyv20/definitions.py
oanda_accessor_pyv20/interface.py
oanda_accessor_pyv20/preprocessor.py
oanda_accessor_pyv20-0.0.6.dist-info/LICENSE
oanda_accessor_pyv20-0.0.6.dist-info/METADATA
oanda_accessor_pyv20-0.0.6.dist-info/WHEEL
oanda_accessor_pyv20-0.0.6.dist-info/top_level.txt
oanda_accessor_pyv20-0.0.6.dist-info/RECORD
