Metadata-Version: 2.1
Name: oanda-accessor-pyv20
Version: 0.0.6
Summary: This app lets you easily load candle data of Foreign Currency from Oanda API.
Home-page: https://github.com/siruku6/oanda_accessor_pyv20
Download-URL: https://github.com/siruku6/oanda_accessor_pyv20
Author: siruku6
Author-email: sirukufarios@gmail.com
Maintainer: siruku6
Maintainer-email: sirukufarios@gmail.com
License: MIT License
Classifier: Topic :: Office/Business :: Financial :: Investment
Classifier: Development Status :: 3 - Alpha
Classifier: Intended Audience :: Developers
Classifier: License :: OSI Approved :: MIT License
Classifier: Programming Language :: Python :: 3
Classifier: Programming Language :: Python :: 3.7
Classifier: Programming Language :: Python :: 3.8
Classifier: Programming Language :: Python :: 3.9
Classifier: Programming Language :: Python :: 3.10
Classifier: Programming Language :: Python :: 3 :: Only
Classifier: Topic :: Software Development :: Libraries :: Python Modules
Requires-Python: >=3.7
License-File: LICENSE
Requires-Dist: oandapyV20 (==0.7.2)
Requires-Dist: pandas (<=1.4.3,>=1.0.0)
Provides-Extra: dev
Requires-Dist: setuptools ; extra == 'dev'
Requires-Dist: twine ; extra == 'dev'
Requires-Dist: wheel ; extra == 'dev'
